MANIFEST.in
README.md
setup.py
bin/userapp
userapp/__init__.py
userapp/cli/__init__.py
userapp/cli/clidriver.py
userapp/cli/command.py
userapp/cli/configuration.py
userapp/cli/core.py
userapp/cli/helper.py
userapp/cli/userapp-cli.py
userapp_cli.egg-info/PKG-INFO
userapp_cli.egg-info/SOURCES.txt
userapp_cli.egg-info/dependency_links.txt
userapp_cli.egg-info/namespace_packages.txt
userapp_cli.egg-info/not-zip-safe
userapp_cli.egg-info/requires.txt
userapp_cli.egg-info/top_level.txt