Metadata-Version: 1.1
Name: userapp-cli
Version: 1.0.0
Summary: Universal Command Line Environment for UserApp.
Home-page: https://github.com/userapp-io/userapp-cli/
Author: Robin Orheden
Author-email: robin.orheden@userapp.io
License: MIT
Keywords: userapp cli
Platform: UNKNOWN
Classifier: Development Status :: 5 - Production/Stable
Classifier: Intended Audience :: Developers
Classifier: Intended Audience :: System Administrators
Classifier: Natural Language :: English
Classifier: License :: OSI Approved :: Apache Software License
Classifier: Programming Language :: Python
Classifier: Programming Language :: Python :: 2.6
Classifier: Programming Language :: Python :: 2.7
Classifier: Programming Language :: Python :: 3
Classifier: Programming Language :: Python :: 3.3
